LICENSE.txt
MANIFEST.in
README.md
README_PyPI.md
pyproject.toml
setup.py
cmfo/__init__.py
cmfo/__main__.py
cmfo/bridge.py
cmfo/cli.py
cmfo/compression.py
cmfo/constants.py
cmfo/server.py
cmfo/verify.py
cmfo/vis.py
cmfo/algebra/__init__.py
cmfo/algebra/fractal_ops.py
cmfo/algebra/roots.py
cmfo/apps/__init__.py
cmfo/apps/cli.py
cmfo/apps/neuron.py
cmfo/bridges/__init__.py
cmfo/bridges/chaos.py
cmfo/bridges/relativity.py
cmfo/bridges/thermodynamics.py
cmfo/compiler/__init__.py
cmfo/compiler/graph.py
cmfo/compiler/jit.py
cmfo/core/__init__.py
cmfo/core/api.py
cmfo/core/fractal.py
cmfo/core/gamma_phi.py
cmfo/core/matrix.py
cmfo/core/native_lib.py
cmfo/core/phi_math.py
cmfo/core/t7_tensor.py
cmfo/geometry/rhombus.py
cmfo/geometry/tilings.py
cmfo/geometry/triangle.py
cmfo/layers/__init__.py
cmfo/layers/attention.py
cmfo/layers/linear.py
cmfo/logic/__init__.py
cmfo/logic/circuits.py
cmfo/logic/fractal_logic.py
cmfo/logic/phi_logic.py
cmfo/memory/__init__.py
cmfo/memory/fractal_memory.py
cmfo/npu/__init__.py
cmfo/npu/instruction_set.py
cmfo/npu/simulator.py
cmfo/physics/__init__.py
cmfo/physics/mass.py
cmfo/superposition/batch.py
cmfo/topology/__init__.py
cmfo/topology/metric.py
cmfo/topology/spectral.py
cmfo_fractal.egg-info/PKG-INFO
cmfo_fractal.egg-info/SOURCES.txt
cmfo_fractal.egg-info/dependency_links.txt
cmfo_fractal.egg-info/entry_points.txt
cmfo_fractal.egg-info/requires.txt
cmfo_fractal.egg-info/top_level.txt
native_src/matrix_engine.cpp
native_src/matrix_engine.hpp