Metadata-Version: 2.4
Name: cmfo-fractal
Version: 1.1.0
Summary: Professional fractal computation framework based on golden ratio (φ) and 7D geometric manifolds
Home-page: https://github.com/1JONMONTERV/CMFO-COMPUTACION-FRACTAL-
Author: Jonathan Montero Viques
Author-email: Jonathan Montero Viquez <jmvlavacar@hotmail.com>
License: Apache-2.0
Project-URL: Homepage, https://1jonmonterv.github.io/CMFO-COMPUTACION-FRACTAL-/
Project-URL: Repository, https://github.com/1JONMONTERV/CMFO-COMPUTACION-FRACTAL-
Keywords: fractal,golden-ratio,phi,geometric-computation,deterministic,algebra,logic,physics,compton,manifold,7d,tensor,optimization,reversible-logic,analog-computing,npu
Classifier: Development Status :: 4 - Beta
Classifier: Intended Audience :: Science/Research
Classifier: Intended Audience :: Developers
Classifier: Intended Audience :: Education
Classifier: License :: OSI Approved :: Apache Software License
Classifier: Programming Language :: Python :: 3
Classifier: Programming Language :: Python :: 3.9
Classifier: Programming Language :: Python :: 3.10
Classifier: Programming Language :: Python :: 3.11
Classifier: Programming Language :: Python :: 3.12
Classifier: Programming Language :: C++
Classifier: Topic :: Scientific/Engineering :: Mathematics
Classifier: Topic :: Scientific/Engineering :: Physics
Classifier: Topic :: Software Development :: Libraries :: Python Modules
Classifier: Operating System :: OS Independent
Requires-Python: >=3.9
License-File: LICENSE.txt
Requires-Dist: numpy>=1.20
Provides-Extra: cuda
Requires-Dist: cupy>=10.0; extra == "cuda"
Provides-Extra: dev
Requires-Dist: pytest>=7.0; extra == "dev"
Requires-Dist: black>=22.0; extra == "dev"
Requires-Dist: mypy>=0.990; extra == "dev"
Requires-Dist: build>=0.10; extra == "dev"
Provides-Extra: docs
Requires-Dist: sphinx>=5.0; extra == "docs"
Requires-Dist: sphinx-rtd-theme>=1.0; extra == "docs"
Dynamic: author
Dynamic: home-page
Dynamic: license-file
Dynamic: requires-python
